discord_fetch/__init__.py
discord_fetch/_modidx.py
discord_fetch/core.py
discord_fetch-0.0.11.dist-info/licenses/LICENSE
discord_fetch-0.0.11.dist-info/METADATA
discord_fetch-0.0.11.dist-info/WHEEL
discord_fetch-0.0.11.dist-info/entry_points.txt
discord_fetch-0.0.11.dist-info/top_level.txt
discord_fetch-0.0.11.dist-info/RECORD
